AUTHORS.rst
MANIFEST.in
README.rst
setup.cfg
setup.py
hcp/__init__.py
hcp/anatomy.py
hcp/preprocessing.py
hcp/viz.py
hcp/io/__init__.py
hcp/io/read.py
hcp/io/file_mapping/__init__.py
hcp/io/file_mapping/file_mapping.py
hcp/io/file_mapping/s3.py
hcp/io/file_mapping/tests/__init__.py
hcp/io/tests/__init__.py
hcp/io/tests/test_io.py
hcp/tests/__init__.py
hcp/tests/config.py
hcp/tests/test_anatomy.py
hcp/tests/test_preprocessing.py
hcp/tests/test_viz.py
mne_hcp.egg-info/PKG-INFO
mne_hcp.egg-info/SOURCES.txt
mne_hcp.egg-info/dependency_links.txt
mne_hcp.egg-info/not-zip-safe
mne_hcp.egg-info/top_level.txt