Metadata-Version: 1.1
Name: mne-hcp
Version: 0.1.dev8
Summary: MNE HCP project for accessing the human connectome MEG data in Python.
Home-page: http://github.com/mne-tools/mne-hcp
Author: Denis A. Engemann
Author-email: denis.engemann@gmail.com
License: BSD (3-clause)
Download-URL: http://github.com/mne-tools/mne-hcp
Platform: any
Classifier: Intended Audience :: Science/Research
Classifier: Intended Audience :: Developers
Classifier: License :: OSI Approved
Classifier: Programming Language :: Python
Classifier: Topic :: Software Development
Classifier: Topic :: Scientific/Engineering
Classifier: Operating System :: Microsoft :: Windows
Classifier: Operating System :: POSIX
Classifier: Operating System :: Unix
Classifier: Operating System :: MacOS
